<annotation>
	<folder>Gato</folder>
	<filename>gato59.jpg</filename>
	<path>C:\Users\anago\OneDrive - Universidad Técnica Federico Santa María\Doggesdelapobla\Clasificador\Dataset\Gato\gato59.jpg</path>
	<source>
		<database>Unknown</database>
	</source>
	<size>
		<width>770</width>
		<height>513</height>
		<depth>3</depth>
	</size>
	<segmented>0</segmented>
	<object>
		<name>cat</name>
		<pose>Unspecified</pose>
		<truncated>0</truncated>
		<difficult>0</difficult>
		<bndbox>
			<xmin>276</xmin>
			<ymin>71</ymin>
			<xmax>627</xmax>
			<ymax>444</ymax>
		</bndbox>
	</object>
</annotation>
