<annotation>
	<folder>gatos</folder>
	<filename>gato240.jpg</filename>
	<path>C:\Users\alici\OneDrive\Escritorio\gatos\gato240.jpg</path>
	<source>
		<database>Unknown</database>
	</source>
	<size>
		<width>526</width>
		<height>822</height>
		<depth>3</depth>
	</size>
	<segmented>0</segmented>
	<object>
		<name>cat</name>
		<pose>Unspecified</pose>
		<truncated>0</truncated>
		<difficult>0</difficult>
		<bndbox>
			<xmin>9</xmin>
			<ymin>28</ymin>
			<xmax>523</xmax>
			<ymax>792</ymax>
		</bndbox>
	</object>
</annotation>
